mig_perf/__init__.py
mig_perf/controller/__init__.py
mig_perf/controller/mig_controller.py
mig_perf/controller/mps_controller.py
mig_perf/exporter/__init__.py
mig_perf/exporter/dcgm_exporter.py
mig_perf/exporter/migperf_exporter.py
mig_perf/profiler/__init__.py
mig_perf/profiler/server/__init__.py
mig_perf/profiler/server/app.py
mig_perf/profiler/server/torch_model_runner.py
mig_perf/profiler/utils/__init__.py
mig_perf/profiler/utils/data_hub.py
mig_perf/profiler/utils/logger.py
mig_perf/profiler/utils/misc.py
mig_perf/profiler/utils/model_hub.py
mig_perf/profiler/utils/pipeline_manager.py
mig_perf/profiler/utils/request.py
migperf-0.0.1.dist-info/LICENSE
migperf-0.0.1.dist-info/METADATA
migperf-0.0.1.dist-info/WHEEL
migperf-0.0.1.dist-info/top_level.txt
migperf-0.0.1.dist-info/RECORD
