Metadata-Version: 2.1
Name: migperf
Version: 0.0.1
Summary: Multi-Instance-GPU profiling tool
Home-page: https://github.com/MLSysOps/MIGProfiler
Download-URL: https://github.com/MLSysOps/MIGProfiler/archive/master.zip
Author: Xing Di
Author-email: xing.cyrildi@gmail.com
Keywords: benchmark,deep learning,MLOps,neural networks
Classifier: Development Status :: 5 - Production/Stable
Classifier: Intended Audience :: Education
Classifier: Intended Audience :: Financial and Insurance Industry
Classifier: Intended Audience :: Science/Research
Classifier: Intended Audience :: Developers
Classifier: Intended Audience :: Information Technology
Classifier: License :: OSI Approved :: MIT License
Classifier: Programming Language :: Python :: 3
Classifier: Operating System :: OS Independent
License-File: LICENSE
Requires-Dist: datasets (==2.4.0)
Requires-Dist: prometheus-client (==0.15.0)
Requires-Dist: sanic (==22.9.1)
Requires-Dist: tqdm (==4.64.1)
Requires-Dist: transformers (==4.25.1)
Requires-Dist: opencv-python
Requires-Dist: torch (==1.13.0)
Requires-Dist: torchvision (==0.14.0)
Requires-Dist: numpy (==1.23.4)
